hug_noop.py
rlacalc/__init__.py
rlacalc-0.4.0.dist-info/entry_points.txt
rlacalc-0.4.0.dist-info/LICENSE
rlacalc-0.4.0.dist-info/WHEEL
rlacalc-0.4.0.dist-info/METADATA
rlacalc-0.4.0.dist-info/RECORD
