Metadata-Version: 2.1
Name: rlacalc
Version: 0.4.0
Summary: Statistical calculations for risk-limiting election tabulation audits (RLAs)
Home-page: http://bcn.boulder.co.us/~neal/electionaudits/rlacalc.html
License: MIT
Keywords: RLA,risk-limiting audit,election,audit
Author: Neal McBurnett
Author-email: neal@mcburnett.org
Requires-Python: >=3.8,<4.0
Classifier: Development Status :: 5 - Production/Stable
Classifier: Environment :: Console
Classifier: Environment :: Web Environment
Classifier: Intended Audience :: Developers
Classifier: Intended Audience :: Science/Research
Classifier: License :: OSI Approved :: MIT License
Classifier: Natural Language :: English
Classifier: Programming Language :: Python :: 3
Classifier: Programming Language :: Python :: 3.10
Classifier: Programming Language :: Python :: 3.8
Classifier: Programming Language :: Python :: 3.9
Classifier: Topic :: Scientific/Engineering :: Mathematics
Classifier: Topic :: Security
Project-URL: Repository, https://github.com/nealmcb/rlacalc
